pyrocatto/__init__.py
pyrocatto/__main__.py
pyrocatto/configurator/__init__.py
pyrocatto/configurator/config_types.py
pyrocatto/configurator/session_loader/__init__.py
pyrocatto/configurator/session_loader/from_yaml.py
pyrocatto/filters/__init__.py
pyrocatto/filters/wheel_user.py
pyrocatto_sg/__init__.py
pyrocatto_sg/__main__.py
pyrocat-1.1.1.dist-info/LICENSE
pyrocat-1.1.1.dist-info/METADATA
pyrocat-1.1.1.dist-info/WHEEL
pyrocat-1.1.1.dist-info/RECORD
